README.md
setup.py
facesync/__init__.py
facesync/facesync.py
facesync/utils.py
facesync/version.py
facesync.egg-info/PKG-INFO
facesync.egg-info/SOURCES.txt
facesync.egg-info/dependency_links.txt
facesync.egg-info/requires.txt
facesync.egg-info/top_level.txt