Metadata-Version: 1.1
Name: facesync
Version: 0.0.9
Summary: A Python package to sync videos based on audio
Home-page: https://github.com/jcheong0428/facesync
Author: Jin Hyun Cheong
Author-email: jcheong.gr@dartmouth.edu
License: LICENSE.txt
Download-URL: https://github.com/jcheong0428/facesync/tarball/0.9
Keywords: psychology,preprocessing,video,audio,facecam,syncing
Platform: UNKNOWN
Classifier: Programming Language :: Python
Classifier: Operating System :: OS Independent
Classifier: Intended Audience :: Science/Research
Classifier: License :: OSI Approved :: MIT License
